pubsub_pull_ce_subscriber/__init__.py
pubsub_pull_ce_subscriber/subscriber.py
pubsub_pull_ce_subscriber-0.1.0.dist-info/METADATA
pubsub_pull_ce_subscriber-0.1.0.dist-info/WHEEL
pubsub_pull_ce_subscriber-0.1.0.dist-info/entry_points.txt
pubsub_pull_ce_subscriber-0.1.0.dist-info/RECORD
